odoo8_addon_stock_picking_backorder_strategy-8.0.0.1.0.99.dev19-nspkg.pth
odoo_addons/stock_picking_backorder_strategy/README.rst
odoo_addons/stock_picking_backorder_strategy/__init__.py
odoo_addons/stock_picking_backorder_strategy/__openerp__.py
odoo_addons/stock_picking_backorder_strategy/i18n/am.po
odoo_addons/stock_picking_backorder_strategy/i18n/bg.po
odoo_addons/stock_picking_backorder_strategy/i18n/bs.po
odoo_addons/stock_picking_backorder_strategy/i18n/ca.po
odoo_addons/stock_picking_backorder_strategy/i18n/ca_ES.po
odoo_addons/stock_picking_backorder_strategy/i18n/cs.po
odoo_addons/stock_picking_backorder_strategy/i18n/de.po
odoo_addons/stock_picking_backorder_strategy/i18n/el_GR.po
odoo_addons/stock_picking_backorder_strategy/i18n/en_AU.po
odoo_addons/stock_picking_backorder_strategy/i18n/en_GB.po
odoo_addons/stock_picking_backorder_strategy/i18n/es.po
odoo_addons/stock_picking_backorder_strategy/i18n/es_AR.po
odoo_addons/stock_picking_backorder_strategy/i18n/es_CL.po
odoo_addons/stock_picking_backorder_strategy/i18n/es_CO.po
odoo_addons/stock_picking_backorder_strategy/i18n/es_CR.po
odoo_addons/stock_picking_backorder_strategy/i18n/es_DO.po
odoo_addons/stock_picking_backorder_strategy/i18n/es_EC.po
odoo_addons/stock_picking_backorder_strategy/i18n/es_MX.po
odoo_addons/stock_picking_backorder_strategy/i18n/es_VE.po
odoo_addons/stock_picking_backorder_strategy/i18n/et.po
odoo_addons/stock_picking_backorder_strategy/i18n/eu.po
odoo_addons/stock_picking_backorder_strategy/i18n/fa.po
odoo_addons/stock_picking_backorder_strategy/i18n/fi.po
odoo_addons/stock_picking_backorder_strategy/i18n/fr.po
odoo_addons/stock_picking_backorder_strategy/i18n/fr_CH.po
odoo_addons/stock_picking_backorder_strategy/i18n/fr_FR.po
odoo_addons/stock_picking_backorder_strategy/i18n/gl.po
odoo_addons/stock_picking_backorder_strategy/i18n/he.po
odoo_addons/stock_picking_backorder_strategy/i18n/hi.po
odoo_addons/stock_picking_backorder_strategy/i18n/hr.po
odoo8_addon_stock_picking_backorder_strategy-8.0.0.1.0.99.dev19.dist-info/METADATA
odoo8_addon_stock_picking_backorder_strategy-8.0.0.1.0.99.dev19.dist-info/WHEEL
odoo8_addon_stock_picking_backorder_strategy-8.0.0.1.0.99.dev19.dist-info/namespace_packages.txt
odoo8_addon_stock_picking_backorder_strategy-8.0.0.1.0.99.dev19.dist-info/top_level.txt
odoo8_addon_stock_picking_backorder_strategy-8.0.0.1.0.99.dev19.dist-info/RECORD
